twweet_cli/Listener.py
twweet_cli/Twweeter.py
twweet_cli/__init__.py
twweet_cli/main.py
twweet_cli/config/ConfigReader.py
twweet_cli/config/__init__.py
twweet_cli-2.1.0.dist-info/LICENSE
twweet_cli-2.1.0.dist-info/METADATA
twweet_cli-2.1.0.dist-info/WHEEL
twweet_cli-2.1.0.dist-info/entry_points.txt
twweet_cli-2.1.0.dist-info/top_level.txt
twweet_cli-2.1.0.dist-info/RECORD
