Metadata-Version: 2.1
Name: twweet-cli
Version: 2.1.0
Summary: Tweet right from your cli without even opening your browser.
Home-page: https://github.com/CruiseDevice/twweet-cli/
Author: Akash Chavan
Author-email: achavan1211@gmail.com
License: MIT
Keywords: twitter tweet cli
Platform: UNKNOWN
Classifier: Development Status :: 5 - Production/Stable
Classifier: License :: OSI Approved :: MIT License
Classifier: Programming Language :: Python :: 3.6
Requires-Python: >=3.6
Requires-Dist: tweepy
Requires-Dist: pyyaml
Requires-Dist: python-dotenv
